CHANGES.txt
LICENSE.txt
MANIFEST.in
README.md
sampleconfig.json
setup.py
AWSSQSAlert/__init__.py
AWSSQSAlert/handlers/Handler.py
AWSSQSAlert/handlers/__init__.py
AWSSQSAlert/handlers/chef_handler.py
AWSSQSAlert/handlers/graphite_handler.py
AWSSQSAlert/test/__init__.py
aws_sqs_alert.egg-info/PKG-INFO
aws_sqs_alert.egg-info/SOURCES.txt
aws_sqs_alert.egg-info/dependency_links.txt
aws_sqs_alert.egg-info/requires.txt
aws_sqs_alert.egg-info/top_level.txt
bin/aws-sqs-alert
bin/init.d/aws-sqs-alert