Metadata-Version: 1.1
Name: aws-sqs-alert
Version: 0.1.0
Summary: Amazon Web Services - Alert on AutoScale or Cloudwatch via SQS
Home-page: https://github.com/Jumpshot/aws-sqs-alert
Author: Alex Corley
Author-email: acorley@anthroprose.com
License: GPLv2
Platform: Posix; MacOS X; Windows
Classifier: Development Status :: 5 - Production/Stable
Classifier: Intended Audience :: Developers
Classifier: Operating System :: OS Independent
Classifier: Topic :: Internet
Classifier: Programming Language :: Python :: 2
Classifier: Programming Language :: Python :: 2.5
Classifier: Programming Language :: Python :: 2.6
Classifier: Programming Language :: Python :: 2.7
